[{"date":1556082000,"excerpt":"META DESCRIPTION GOES HERE","objectID":"4038b616b763c64f63837e70b0cba34a","title":"About Us","type":"page","url":"https://sacredspace.netlify.com/about/"},{"date":1556082000,"excerpt":"META DESCRIPTION GOES HERE","objectID":"b98533529a4a228bb1b51b52effd5f9f","title":"Classes","type":"page","url":"https://sacredspace.netlify.com/classes/"},{"date":1556082000,"excerpt":"META DESCRIPTION GOES HERE","objectID":"175ae1237a7c09be58e1974efbb05e10","title":"Contact Us","type":"page","url":"https://sacredspace.netlify.com/contact/"},{"date":1556082000,"excerpt":"META DESCRIPTION GOES HERE","objectID":"9a3e0423437ead52d675e717730dd8bd","title":"Dig Deep","type":"page","url":"https://sacredspace.netlify.com/dig-deep/"},{"date":1556082000,"excerpt":"META DESCRIPTION GOES HERE","objectID":"f85a1424ab9523056b692a9693c0c7c9","title":"FAQS","type":"page","url":"https://sacredspace.netlify.com/faqs/"},{"date":1556082000,"excerpt":"Default meta desciption for the page.","objectID":"3976528693a0108357f4928017600865","title":"Home","type":"page","url":"https://sacredspace.netlify.com/"},{"date":1556082000,"excerpt":"META DESCRIPTION GOES HERE","objectID":"99962908e08aaeb19e7d88fc2f92f4a6","title":"Pricing","type":"page","url":"https://sacredspace.netlify.com/pricing/"},{"date":1556082000,"excerpt":"META DESCRIPTION GOES HERE","objectID":"b14ca643242ffc49c08a52efcb1cfb3a","title":"Sacred Service","type":"page","url":"https://sacredspace.netlify.com/sacred-service/"},{"date":1556082000,"excerpt":"META DESCRIPTION GOES HERE","objectID":"3885e0598d398dfe4d75cbabf4707170","title":"Schedule","type":"page","url":"https://sacredspace.netlify.com/schedule/"},{"date":1556082000,"excerpt":"META DESCRIPTION GOES HERE","objectID":"e80be677534d65fd3daca96050f94c7b","title":"Studio Ettiquette","type":"page","url":"https://sacredspace.netlify.com/etiquette/"},{"date":1556082000,"excerpt":"META DESCRIPTION GOES HERE","objectID":"69a3597aeb98ee9254a52a500cf1759e","title":"Teacher Training","type":"page","url":"https://sacredspace.netlify.com/teacher-training/"},{"date":1556082000,"excerpt":"Thank you - we will be in touch soon.","objectID":"0ae1a2260d8c90c16eba7a4f70d37685","title":"Thank You","type":"page","url":"https://sacredspace.netlify.com/thank-you/"},{"date":-62135596800,"excerpt":null,"objectID":"0f4c98f5934ffa10133bd166396333e1","title":"","type":"page","url":"https://sacredspace.netlify.com/faqs/"},{"date":-62135596800,"excerpt":null,"objectID":"c973267586a3730282c99d040e9163f6","title":"","type":"page","url":"https://sacredspace.netlify.com/partners/"},{"date":-62135596800,"excerpt":null,"objectID":"6101a1fbd930f8b417801500ccb3900d","title":"","type":"page","url":"https://sacredspace.netlify.com/rates/"},{"date":-62135596800,"excerpt":null,"objectID":"edf3b9c4659d6114be79d56b83e83467","title":"","type":"page","url":"https://sacredspace.netlify.com/team/"},{"date":-62135596800,"excerpt":null,"objectID":"ecab3e7b7b6c1c15cef66cd84562f7f4","title":"","type":"page","url":"https://sacredspace.netlify.com/testimonials/"}]